create_python_proj/__init__.py
create_python_proj/main.py
create_python_proj.sh
create_python_proj-1.0.6.dist-info/LICENSE
create_python_proj-1.0.6.dist-info/METADATA
create_python_proj-1.0.6.dist-info/WHEEL
create_python_proj-1.0.6.dist-info/entry_points.txt
create_python_proj-1.0.6.dist-info/RECORD
