Metadata-Version: 2.1
Name: create-python-proj
Version: 1.0.6
Summary: Set up a modern Python project by running one command.
License: MIT
Author: wiresv
Author-email: austinhwx@gmail.com
Requires-Python: >=3.11,<4.0
Classifier: License :: OSI Approved :: MIT License
Classifier: Programming Language :: Python :: 3
Classifier: Programming Language :: Python :: 3.11
Project-URL: Source Code, https://github.com/wiresv/create-python-proj
